rtl/alu_control.v
// ============================================================
//  ALU Control Unit
//  RISC-V 5-Stage Pipeline CPU
// ============================================================
//  This sits BETWEEN the main Control Unit and the ALU.
//  The main control unit gives a 2-bit alu_op.
//  This unit refines it using funct3 + funct7 to produce
//  the exact 4-bit alu_ctrl signal the ALU needs.
//
//  alu_op encoding (from main Control Unit):
//    2'b00  → ADD  (for load/store address calculation)
//    2'b01  → SUB  (for branch comparison)
//    2'b10  → look at funct3/funct7 (R-type and I-type)
//
//  Inputs:
//    alu_op   [1:0]  from main control unit
//    funct3   [2:0]  bits [14:12] of instruction
//    funct7_5 [0:0]  bit  [30]    of instruction (SUB vs ADD, SRA vs SRL)
//    is_imm          1 = I-type immediate (ignore funct7 for ADD/SRL)
//
//  Output:
//    alu_ctrl [3:0]  sent directly to ALU
// ============================================================

`timescale 1ns/1ps

module alu_control (
    input  wire [1:0] alu_op,
    input  wire [2:0] funct3,
    input  wire       funct7_5,   // instruction[30]
    input  wire       is_imm,     // 1 for I-type (addi, xori, etc.)
    output reg  [3:0] alu_ctrl
);

    always @(*) begin
        case (alu_op)
            // Load / Store → always ADD (base + offset)
            2'b00: alu_ctrl = 4'b0000;  // ADD

            // Branch → always SUB (a - b, check zero flag)
            2'b01: alu_ctrl = 4'b0001;  // SUB

            // R-type or I-type: decode funct3 (and funct7 for R-type)
            2'b10: begin
                case (funct3)
                    3'b000: begin
                        // ADD vs SUB: funct7[5]=1 AND it's R-type → SUB
                        if (funct7_5 && !is_imm)
                            alu_ctrl = 4'b0001; // SUB
                        else
                            alu_ctrl = 4'b0000; // ADD / ADDI
                    end
                    3'b001: alu_ctrl = 4'b0101; // SLL / SLLI
                    3'b010: alu_ctrl = 4'b1000; // SLT / SLTI
                    3'b011: alu_ctrl = 4'b1001; // SLTU / SLTIU
                    3'b100: alu_ctrl = 4'b0100; // XOR / XORI
                    3'b101: begin
                        // SRL vs SRA
                        if (funct7_5)
                            alu_ctrl = 4'b0111; // SRA / SRAI
                        else
                            alu_ctrl = 4'b0110; // SRL / SRLI
                    end
                    3'b110: alu_ctrl = 4'b0011; // OR  / ORI
                    3'b111: alu_ctrl = 4'b0010; // AND / ANDI
                    default: alu_ctrl = 4'b0000;
                endcase
            end

            default: alu_ctrl = 4'b0000;
        endcase
    end

endmodule

rtl/alu.v
// ============================================================
//  ALU — Arithmetic Logic Unit
//  RISC-V 5-Stage Pipeline CPU
// ============================================================
//  Inputs:
//    a        [31:0]  — operand A (from register rs1)
//    b        [31:0]  — operand B (register rs2 OR immediate)
//    alu_ctrl [ 3:0]  — operation select (from ALU Control Unit)
//
//  Outputs:
//    result   [31:0]  — computed result
//    zero             — 1 if result == 0  (used by branch logic)
//
//  Operation encoding (alu_ctrl):
//    4'b0000  ADD
//    4'b0001  SUB
//    4'b0010  AND
//    4'b0011  OR
//    4'b0100  XOR
//    4'b0101  SLL  (shift left logical)
//    4'b0110  SRL  (shift right logical)
//    4'b0111  SRA  (shift right arithmetic)
//    4'b1000  SLT  (set less than, signed)
//    4'b1001  SLTU (set less than, unsigned)
// ============================================================

`timescale 1ns/1ps

module alu (
    input  wire [31:0] a,
    input  wire [31:0] b,
    input  wire [ 3:0] alu_ctrl,
    output reg  [31:0] result,
    output wire        zero
);

    // zero flag: high when result is 0 (used for BEQ/BNE)
    assign zero = (result == 32'b0);

    // shift amount comes from lower 5 bits of b
    wire [4:0] shamt = b[4:0];

    always @(*) begin
        case (alu_ctrl)
            4'b0000: result = a + b;                          // ADD
            4'b0001: result = a - b;                          // SUB
            4'b0010: result = a & b;                          // AND
            4'b0011: result = a | b;                          // OR
            4'b0100: result = a ^ b;                          // XOR
            4'b0101: result = a << shamt;                     // SLL
            4'b0110: result = a >> shamt;                     // SRL
            4'b0111: result = $signed(a) >>> shamt;           // SRA
            4'b1000: result = ($signed(a) < $signed(b))       // SLT
                               ? 32'd1 : 32'd0;
            4'b1001: result = (a < b) ? 32'd1 : 32'd0;       // SLTU
            default: result = 32'b0;                          // safety default
        endcase
    end
endmodule

tb/tb_alu.v
// ============================================================
//  Testbench — ALU + ALU Control Unit
//  RISC-V 5-Stage Pipeline CPU
// ============================================================
//  Tests every ALU operation with multiple cases including:
//    - normal values
//    - zero inputs
//    - negative numbers (signed)
//    - overflow edge cases
//    - shift amounts
//  Run:  iverilog -o sim/alu_sim rtl/alu.v rtl/alu_control.v tb/tb_alu.v
//        vvp sim/alu_sim
//        gtkwave sim/alu_dump.vcd
// ============================================================

`timescale 1ns/1ps

module tb_alu;

    // ── DUT signals ──────────────────────────────────────────
    reg  [31:0] a, b;
    reg  [ 3:0] alu_ctrl;
    wire [31:0] result;
    wire        zero;

    // ALU Control signals (for alu_control DUT)
    reg  [1:0] alu_op;
    reg  [2:0] funct3;
    reg        funct7_5;
    reg        is_imm;
    wire [3:0] ctrl_out;

    // ── Instantiate ALU ──────────────────────────────────────
    alu uut_alu (
        .a        (a),
        .b        (b),
        .alu_ctrl (alu_ctrl),
        .result   (result),
        .zero     (zero)
    );

    // ── Instantiate ALU Control Unit ─────────────────────────
    alu_control uut_ctrl (
        .alu_op   (alu_op),
        .funct3   (funct3),
        .funct7_5 (funct7_5),
        .is_imm   (is_imm),
        .alu_ctrl (ctrl_out)
    );

    // ── VCD dump for GTKWave ─────────────────────────────────
    initial begin
        $dumpfile("sim/alu_dump.vcd");
        $dumpvars(0, tb_alu);
    end

    // ── Helper task: check result ─────────────────────────────
    integer pass_count, fail_count;

    task check;
        input [63:0] expected;
        input [80*8:1] test_name;
        begin
            #1; // let combinational logic settle
            if (result === expected[31:0]) begin
                $display("  PASS  %-30s | a=%0d b=%0d → result=%0d",
                         test_name, $signed(a), $signed(b), $signed(result));
                pass_count = pass_count + 1;
            end else begin
                $display("  FAIL  %-30s | a=%0d b=%0d → got=%0d, expected=%0d",
                         test_name, $signed(a), $signed(b),
                         $signed(result), $signed(expected));
                fail_count = fail_count + 1;
            end
        end
    endtask

    // ── Main test sequence ────────────────────────────────────
    initial begin
        pass_count = 0;
        fail_count = 0;

        $display("\n========================================");
        $display("  RISC-V ALU Testbench Starting...");
        $display("========================================\n");

        // ─────────────────────────────────────────
        //  ADD  (4'b0000)
        // ─────────────────────────────────────────
        $display("--- ADD ---");
        alu_ctrl = 4'b0000;

        a = 32'd10;     b = 32'd20;     check(32'd30,          "10 + 20 = 30");
        a = 32'd0;      b = 32'd0;      check(32'd0,           "0 + 0 = 0");
        a = 32'hFFFFFFFF; b = 32'd1;   check(32'd0,           "overflow wrap");
        a = -32'd50;    b = 32'd50;     check(32'd0,           "-50 + 50 = 0");
        a = 32'h7FFFFFFF; b = 32'd1;  check(32'h80000000,    "max+1 overflow");

        // ─────────────────────────────────────────
        //  SUB  (4'b0001)
        // ─────────────────────────────────────────
        $display("\n--- SUB ---");
        alu_ctrl = 4'b0001;

        a = 32'd50;     b = 32'd30;     check(32'd20,          "50 - 30 = 20");
        a = 32'd30;     b = 32'd50;     check(-32'd20,         "30 - 50 = -20");
        a = 32'd0;      b = 32'd0;      check(32'd0,           "0 - 0 = 0");
        a = 32'd100;    b = 32'd100;    check(32'd0,           "same values = 0");

        // ─────────────────────────────────────────
        //  AND  (4'b0010)
        // ─────────────────────────────────────────
        $display("\n--- AND ---");
        alu_ctrl = 4'b0010;

        a = 32'hFF00FF00; b = 32'hF0F0F0F0; check(32'hF000F000, "AND pattern");
        a = 32'hFFFFFFFF; b = 32'h00000000; check(32'h00000000, "AND with 0");
        a = 32'hFFFFFFFF; b = 32'hFFFFFFFF; check(32'hFFFFFFFF, "AND all 1s");

        // ─────────────────────────────────────────
        //  OR   (4'b0011)
        // ─────────────────────────────────────────
        $display("\n--- OR ---");
        alu_ctrl = 4'b0011;

        a = 32'hFF00FF00; b = 32'h00FF00FF; check(32'hFFFFFFFF, "OR complement");
        a = 32'h00000000; b = 32'h00000000; check(32'h00000000, "OR all zeros");
        a = 32'hA0A0A0A0; b = 32'h0F0F0F0F; check(32'hAFAFAFAF, "OR pattern");

        // ─────────────────────────────────────────
        //  XOR  (4'b0100)
        // ─────────────────────────────────────────
        $display("\n--- XOR ---");
        alu_ctrl = 4'b0100;

        a = 32'hFFFFFFFF; b = 32'hFFFFFFFF; check(32'h00000000, "XOR same = 0");
        a = 32'hFFFFFFFF; b = 32'h00000000; check(32'hFFFFFFFF, "XOR with 0");
        a = 32'hA5A5A5A5; b = 32'h5A5A5A5A; check(32'hFFFFFFFF, "XOR checkerboard");

        // ─────────────────────────────────────────
        //  SLL  (4'b0101)
        // ─────────────────────────────────────────
        $display("\n--- SLL (Shift Left Logical) ---");
        alu_ctrl = 4'b0101;

        a = 32'd1;      b = 32'd4;      check(32'd16,          "1 << 4 = 16");
        a = 32'd1;      b = 32'd31;     check(32'h80000000,    "1 << 31");
        a = 32'hFFFFFFFF; b = 32'd1;   check(32'hFFFFFFFE,    "0xFFFF << 1");

        // ─────────────────────────────────────────
        //  SRL  (4'b0110)
        // ─────────────────────────────────────────
        $display("\n--- SRL (Shift Right Logical) ---");
        alu_ctrl = 4'b0110;

        a = 32'd16;     b = 32'd4;      check(32'd1,           "16 >> 4 = 1");
        a = 32'h80000000; b = 32'd1;   check(32'h40000000,    "logical: no sign ext");
        a = 32'hFFFFFFFF; b = 32'd4;   check(32'h0FFFFFFF,    "0xFF >> 4 logical");

        // ─────────────────────────────────────────
        //  SRA  (4'b0111)
        // ─────────────────────────────────────────
        $display("\n--- SRA (Shift Right Arithmetic) ---");
        alu_ctrl = 4'b0111;

        a = 32'h80000000; b = 32'd1;   check(32'hC0000000,    "SRA sign extends");
        a = 32'hFFFFFFFF; b = 32'd4;   check(32'hFFFFFFFF,    "all 1s stays all 1s");
        a = 32'd16;       b = 32'd4;   check(32'd1,            "positive same as SRL");

        // ─────────────────────────────────────────
        //  SLT  (4'b1000)
        // ─────────────────────────────────────────
        $display("\n--- SLT (Set Less Than, signed) ---");
        alu_ctrl = 4'b1000;

        a = 32'd5;      b = 32'd10;    check(32'd1,            "5 < 10 → 1");
        a = 32'd10;     b = 32'd5;     check(32'd0,            "10 < 5 → 0");
        a = -32'd1;     b = 32'd0;     check(32'd1,            "-1 < 0 → 1 (signed)");
        a = 32'd0;      b = 32'd0;     check(32'd0,            "equal → 0");

        // ─────────────────────────────────────────
        //  SLTU (4'b1001)
        // ─────────────────────────────────────────
        $display("\n--- SLTU (Set Less Than, unsigned) ---");
        alu_ctrl = 4'b1001;

        a = 32'd5;        b = 32'd10;       check(32'd1,       "5 < 10 → 1");
        a = 32'hFFFFFFFF; b = 32'd1;        check(32'd0,       "big > 1 unsigned → 0");
        a = 32'd1;        b = 32'hFFFFFFFF; check(32'd1,       "1 < big unsigned → 1");

        // ─────────────────────────────────────────
        //  Zero Flag Tests
        // ─────────────────────────────────────────
        $display("\n--- ZERO FLAG ---");
        alu_ctrl = 4'b0001; // SUB
        a = 32'd42; b = 32'd42;
        #1;
        if (zero === 1'b1)
            $display("  PASS  zero flag when equal            | a=%0d b=%0d zero=%b", a, b, zero);
        else
            $display("  FAIL  zero flag when equal            | expected 1, got %b", zero);

        a = 32'd42; b = 32'd43;
        #1;
        if (zero === 1'b0)
            $display("  PASS  zero flag when unequal          | a=%0d b=%0d zero=%b", a, b, zero);
        else
            $display("  FAIL  zero flag when unequal          | expected 0, got %b", zero);

        // ─────────────────────────────────────────
        //  ALU CONTROL UNIT Tests
        // ─────────────────────────────────────────
        $display("\n--- ALU CONTROL UNIT ---");
        is_imm = 0;

        // Load/Store → ADD
        alu_op = 2'b00; funct3 = 3'bxxx; funct7_5 = 0;
        #1;
        if (ctrl_out === 4'b0000)
            $display("  PASS  alu_op=00 (load/store) → ADD");
        else
            $display("  FAIL  alu_op=00 → expected ADD(0000) got %b", ctrl_out);

        // Branch → SUB
        alu_op = 2'b01; funct3 = 3'bxxx; funct7_5 = 0;
        #1;
        if (ctrl_out === 4'b0001)
            $display("  PASS  alu_op=01 (branch)     → SUB");
        else
            $display("  FAIL  alu_op=01 → expected SUB(0001) got %b", ctrl_out);

        // R-type ADD
        alu_op = 2'b10; funct3 = 3'b000; funct7_5 = 0; is_imm = 0;
        #1;
        if (ctrl_out === 4'b0000)
            $display("  PASS  R-type funct3=000 f7=0 → ADD");
        else
            $display("  FAIL  R-type ADD → got %b", ctrl_out);

        // R-type SUB
        alu_op = 2'b10; funct3 = 3'b000; funct7_5 = 1; is_imm = 0;
        #1;
        if (ctrl_out === 4'b0001)
            $display("  PASS  R-type funct3=000 f7=1 → SUB");
        else
            $display("  FAIL  R-type SUB → got %b", ctrl_out);

        // I-type ADDI (funct7_5=1 but is_imm=1 → should still be ADD)
        alu_op = 2'b10; funct3 = 3'b000; funct7_5 = 1; is_imm = 1;
        #1;
        if (ctrl_out === 4'b0000)
            $display("  PASS  I-type ADDI (f7=1 ignored) → ADD");
        else
            $display("  FAIL  I-type ADDI → expected ADD got %b", ctrl_out);

        // ─────────────────────────────────────────
        //  Summary
        // ─────────────────────────────────────────
        $display("\n========================================");
        $display("  Results: %0d passed, %0d failed", pass_count, fail_count);
        $display("========================================\n");

        $finish;
    end

endmodule

sim/alu_dump.vcd
$date
	Fri May 29 01:08:09 2026
$end
$version
	Icarus Verilog
$end
$timescale
	1ps
$end
$scope module tb_alu $end
$var wire 1 ! zero $end
$var wire 32 " result [31:0] $end
$var wire 4 # ctrl_out [3:0] $end
$var reg 32 $ a [31:0] $end
$var reg 4 % alu_ctrl [3:0] $end
$var reg 2 & alu_op [1:0] $end
$var reg 32 ' b [31:0] $end
$var reg 3 ( funct3 [2:0] $end
$var reg 1 ) funct7_5 $end
$var reg 1 * is_imm $end
$var integer 32 + fail_count [31:0] $end
$var integer 32 , pass_count [31:0] $end
$scope module uut_alu $end
$var wire 32 - a [31:0] $end
$var wire 4 . alu_ctrl [3:0] $end
$var wire 32 / b [31:0] $end
$var wire 1 ! zero $end
$var wire 5 0 shamt [4:0] $end
$var reg 32 1 result [31:0] $end
$upscope $end
$scope module uut_ctrl $end
$var wire 2 2 alu_op [1:0] $end
$var wire 3 3 funct3 [2:0] $end
$var wire 1 ) funct7_5 $end
$var wire 1 * is_imm $end
$var reg 4 4 alu_ctrl [3:0] $end
$upscope $end
$scope task check $end
$var reg 64 5 expected [63:0] $end
$var reg 640 6 test_name [640:1] $end
$upscope $end
$upscope $end
$enddefinitions $end
$comment Show the parameter values. $end
$dumpall
$end
#0
$dumpvars
b1100010011000000100000001010110010000000110010001100000010000000111101001000000011001100110000 6
b11110 5
bx 4
bx 3
bx 2
b11110 1
b10100 0
b10100 /
b0 .
b1010 -
b0 ,
b0 +
x*
x)
bx (
b10100 '
bx &
b0 %
b1010 $
bx #
b11110 "
0!
$end
#1000
b0 0
1!
b0 "
b0 1
b1100000010000000101011001000000011000000100000001111010010000000110000 6
b0 5
b0 '
b0 /
b0 $
b0 -
b1 ,
#2000
b1 0
b1101111011101100110010101110010011001100110110001101111011101110010000001110111011100100110000101110000 6
b1 '
b1 /
b11111111111111111111111111111111 $
b11111111111111111111111111111111 -
b10 ,
#3000
b10010 0
b1011010011010100110000001000000010101100100000001101010011000000100000001111010010000000110000 6
b110010 '
b110010 /
b11111111111111111111111111001110 $
b11111111111111111111111111001110 -
b11 ,
#4000
b1 0
0!
b10000000000000000000000000000000 "
b10000000000000000000000000000000 1
b110110101100001011110000010101100110001001000000110111101110110011001010111001001100110011011000110111101110111 6
b10000000000000000000000000000000 5
b1 '
b1 /
b1111111111111111111111111111111 $
b1111111111111111111111111111111 -
b100 ,
#5000
b11110 0
b10100 "
b10100 1
b1101010011000000100000001011010010000000110011001100000010000000111101001000000011001000110000 6
b10100 5
b11110 '
b11110 /
b110010 $
b110010 -
b1 %
b1 .
b101 ,
#6000
b10010 0
b11111111111111111111111111101100 "
b11111111111111111111111111101100 1
b110011001100000010000000101101001000000011010100110000001000000011110100100000001011010011001000110000 6
b1111111111111111111111111111111111111111111111111111111111101100 5
b110010 '
b110010 /
b11110 $
b11110 -
b110 ,
#7000
b0 0
1!
b0 "
b0 1
b1100000010000000101101001000000011000000100000001111010010000000110000 6
b0 5
b0 '
b0 /
b0 $
b0 -
b111 ,
#8000
b100 0
b11100110110000101101101011001010010000001110110011000010110110001110101011001010111001100100000001111010010000000110000 6
b1100100 '
b1100100 /
b1100100 $
b1100100 -
b1000 ,
#9000
b10000 0
0!
b11110000000000001111000000000000 "
b11110000000000001111000000000000 1
b100000101001110010001000010000001110000011000010111010001110100011001010111001001101110 6
b11110000000000001111000000000000 5
b11110000111100001111000011110000 '
b11110000111100001111000011110000 /
b11111111000000001111111100000000 $
b11111111000000001111111100000000 -
b10 %
b10 .
b1001 ,
#10000
b0 0
1!
b0 "
b0 1
b1000001010011100100010000100000011101110110100101110100011010000010000000110000 6
b0 5
b0 '
b0 /
b11111111111111111111111111111111 $
b11111111111111111111111111111111 -
b1010 ,
#11000
0!
b11111111111111111111111111111111 "
b11111111111111111111111111111111 1
b11111 0
b1000001010011100100010000100000011000010110110001101100001000000011000101110011 6
b11111111111111111111111111111111 5
b11111111111111111111111111111111 '
b11111111111111111111111111111111 /
b1011 ,
#12000
b1001111010100100010000001100011011011110110110101110000011011000110010101101101011001010110111001110100 6
b111111110000000011111111 '
b111111110000000011111111 /
b11111111000000001111111100000000 $
b11111111000000001111111100000000 -
b11 %
b11 .
b1100 ,
#13000
b0 0
1!
b0 "
b0 1
b10011110101001000100000011000010110110001101100001000000111101001100101011100100110111101110011 6
b0 5
b0 '
b0 /
b0 $
b0 -
b1101 ,
#14000
b1111 0
0!
b10101111101011111010111110101111 "
b10101111101011111010111110101111 1
b1001111010100100010000001110000011000010111010001110100011001010111001001101110 6
b10101111101011111010111110101111 5
b1111000011110000111100001111 '
b1111000011110000111100001111 /
b10100000101000001010000010100000 $
b10100000101000001010000010100000 -
b1110 ,
#15000
b11111 0
1!
b0 "
b0 1
b10110000100111101010010001000000111001101100001011011010110010100100000001111010010000000110000 6
b0 5
b11111111111111111111111111111111 '
b11111111111111111111111111111111 /
b11111111111111111111111111111111 $
b11111111111111111111111111111111 -
b100 %
b100 .
b1111 ,
#16000
0!
b11111111111111111111111111111111 "
b11111111111111111111111111111111 1
b0 0
b1011000010011110101001000100000011101110110100101110100011010000010000000110000 6
b11111111111111111111111111111111 5
b0 '
b0 /
b10000 ,
#17000
b11010 0
b1011000010011110101001000100000011000110110100001100101011000110110101101100101011100100110001001101111011000010111001001100100 6
b1011010010110100101101001011010 '
b1011010010110100101101001011010 /
b10100101101001011010010110100101 $
b10100101101001011010010110100101 -
b10001 ,
#18000
b100 0
b10000 "
b10000 1
b11000100100000001111000011110000100000001101000010000000111101001000000011000100110110 6
b10000 5
b100 '
b100 /
b1 $
b1 -
b101 %
b101 .
b10010 ,
#19000
b10000000000000000000000000000000 "
b10000000000000000000000000000000 1
b11111 0
b110001001000000011110000111100001000000011001100110001 6
b10000000000000000000000000000000 5
b11111 '
b11111 /
b10011 ,
#20000
b11111111111111111111111111111110 "
b11111111111111111111111111111110 1
b1 0
b11000001111000010001100100011001000110010001100010000000111100001111000010000000110001 6
b11111111111111111111111111111110 5
b1 '
b1 /
b11111111111111111111111111111111 $
b11111111111111111111111111111111 -
b10100 ,
#21000
b100 0
b1 "
b1 1
b11000100110110001000000011111000111110001000000011010000100000001111010010000000110001 6
b1 5
b100 '
b100 /
b10000 $
b10000 -
b110 %
b110 .
b10101 ,
#22000
b1 0
b1000000000000000000000000000000 "
b1000000000000000000000000000000 1
b110110001101111011001110110100101100011011000010110110000111010001000000110111001101111001000000111001101101001011001110110111000100000011001010111100001110100 6
b1000000000000000000000000000000 5
b1 '
b1 /
b10000000000000000000000000000000 $
b10000000000000000000000000000000 -
b10110 ,
#23000
b100 0
b1111111111111111111111111111 "
b1111111111111111111111111111 1
b11000001111000010001100100011000100000001111100011111000100000001101000010000001101100011011110110011101101001011000110110000101101100 6
b1111111111111111111111111111 5
b100 '
b100 /
b11111111111111111111111111111111 $
b11111111111111111111111111111111 -
b10111 ,
#24000
b1 0
b11000000000000000000000000000000 "
b11000000000000000000000000000000 1
b1010011010100100100000100100000011100110110100101100111011011100010000001100101011110000111010001100101011011100110010001110011 6
b11000000000000000000000000000000 5
b1 '
b1 /
b10000000000000000000000000000000 $
b10000000000000000000000000000000 -
b111 %
b111 .
b11000 ,
#25000
b100 0
b11111111111111111111111111111111 "
b11111111111111111111111111111111 1
b1100001011011000110110000100000001100010111001100100000011100110111010001100001011110010111001100100000011000010110110001101100001000000011000101110011 6
b11111111111111111111111111111111 5
b100 '
b100 /
b11111111111111111111111111111111 $
b11111111111111111111111111111111 -
b11001 ,
#26000
b1 "
b1 1
b111000001101111011100110110100101110100011010010111011001100101001000000111001101100001011011010110010100100000011000010111001100100000010100110101001001001100 6
b1 5
b10000 $
b10000 -
b11010 ,
#27000
b1010 0
b1101010010000000111100001000001111111111111111111111111110001011111111100100100010000000110001 6
b1010 '
b1010 /
b101 $
b101 -
b1000 %
b1000 .
b11011 ,
#28000
b101 0
1!
b0 "
b0 1
b1100010011000000100000001111001111111111111111111111111110001011111111100100100010000000110000 6
b0 5
b101 '
b101 /
b1010 $
b1010 -
b11100 ,
#29000
b0 0
0!
b1 "
b1 1
b1011010011000100100000001111000010000011111111111111111111111110000110100100100010000000110001001000000010100001110011011010010110011101101110011001010110010000101001 6
b1 5
b0 '
b0 /
b11111111111111111111111111111111 $
b11111111111111111111111111111111 -
b11101 ,
#30000
1!
b0 "
b0 1
b110010101110001011101011111111111111111111111111110001011111111100100100010000000110000 6
b0 5
b0 $
b0 -
b11110 ,
#31000
b1010 0
0!
b1 "
b1 1
b1101010010000000111100001000001111111111111111111111111110001011111111100100100010000000110001 6
b1 5
b1010 '
b1010 /
b101 $
b101 -
b1001 %
b1001 .
b11111 ,
#32000
b1 0
1!
b0 "
b0 1
b1100010011010010110011100100000001111100010000000110001001000000111010101101110011100110110100101100111011011101111111111111111111111111110001011111111100100100010000000110000 6
b0 5
b1 '
b1 /
b11111111111111111111111111111111 $
b11111111111111111111111111111111 -
b100000 ,
#33000
b11111 0
0!
b1 "
b1 1
b110001001000000011110000100000011000100110100101100111001000000111010101101110011100110110100101100111011011101111111111111111111111111110001011111111100100100010000000110001 6
b1 5
b11111111111111111111111111111111 '
b11111111111111111111111111111111 /
b1 $
b1 -
b100001 ,
#34000
b1010 0
1!
b0 "
b0 1
b101010 '
b101010 /
b101010 $
b101010 -
b1 %
b1 .
b100010 ,
#35000
0!
b11111111111111111111111111111111 "
b11111111111111111111111111111111 1
b1011 0
b101011 '
b101011 /
#36000
b0 #
b0 4
0)
b0 &
b0 2
0*
#37000
b1 #
b1 4
b1 &
b1 2
#38000
b0 #
b0 4
b0 (
b0 3
b10 &
b10 2
#39000
b1 #
b1 4
1)
#40000
b0 #
b0 4
1*
