rtl/register_file.v
// ============================================================
//  Register File
//  RISC-V 5-Stage Pipeline CPU
// ============================================================
//  RISC-V has 32 general-purpose registers: x0 to x31
//  Each register is 32 bits wide.
//
//  Key rules:
//    - x0 is HARDWIRED to 0. Writing to it does nothing.
//    - Two READ ports (rs1, rs2) — read happens every cycle
//    - One WRITE port (rd)       — write happens on clock edge
//
//  Why 2 read ports?
//    Most R-type instructions need TWO source registers.
//    e.g.  add x3, x1, x2  → need to read x1 AND x2 same cycle
//
//  Ports:
//    clk              clock
//    rs1_addr [4:0]   address of source register 1  (0–31)
//    rs2_addr [4:0]   address of source register 2  (0–31)
//    rd_addr  [4:0]   address of destination register
//    rd_data  [31:0]  data to write into rd
//    reg_write        1 = write enabled, 0 = no write
//    rs1_data [31:0]  data read from rs1
//    rs2_data [31:0]  data read from rs2
// ============================================================

`timescale 1ns/1ps

module register_file (
    input  wire        clk,
    // Read ports
    input  wire [ 4:0] rs1_addr,
    input  wire [ 4:0] rs2_addr,
    output wire [31:0] rs1_data,
    output wire [31:0] rs2_data,
    // Write port
    input  wire [ 4:0] rd_addr,
    input  wire [31:0] rd_data,
    input  wire        reg_write
);

    // 32 registers, each 32 bits wide
    reg [31:0] registers [0:31];

    // ── Initialize all registers to 0 ────────────────────────
    integer i;
    initial begin
        for (i = 0; i < 32; i = i + 1)
            registers[i] = 32'b0;
    end

    // ── READ (combinational — instant, no clock needed) ──────
    // x0 is hardwired to 0: if address is 0, always return 0
   assign rs1_data = (rs1_addr == 5'b0)                ? 32'b0   :
                  (reg_write && rd_addr == rs1_addr) ? rd_data :
                  registers[rs1_addr];
    assign rs2_data = (rs2_addr == 5'b0)                       ? 32'b0   :
                  (reg_write && rd_addr == rs2_addr)        ? rd_data :
                  registers[rs2_addr];

    // ── WRITE (sequential — only on rising clock edge) ───────
    always @(posedge clk) begin
        if (reg_write && rd_addr != 5'b0)   // never write to x0
            registers[rd_addr] <= rd_data;
    end

endmodule

tb/tb_register_file.v
// ============================================================
//  Testbench — Register File
//  RISC-V 5-Stage Pipeline CPU
// ============================================================
//  Run:
//    iverilog -o sim/rf_sim.vvp rtl/register_file.v tb/tb_register_file.v
//    vvp sim/rf_sim.vvp
//    gtkwave sim/rf_dump.vcd
// ============================================================

`timescale 1ns/1ps

module tb_register_file;

    // ── DUT signals ──────────────────────────────────────────
    reg        clk;
    reg  [4:0] rs1_addr, rs2_addr, rd_addr;
    reg  [31:0] rd_data;
    reg        reg_write;
    wire [31:0] rs1_data, rs2_data;

    // ── Instantiate DUT ──────────────────────────────────────
    register_file uut (
        .clk       (clk),
        .rs1_addr  (rs1_addr),
        .rs2_addr  (rs2_addr),
        .rs1_data  (rs1_data),
        .rs2_data  (rs2_data),
        .rd_addr   (rd_addr),
        .rd_data   (rd_data),
        .reg_write (reg_write)
    );

    // ── Clock: toggles every 5ns → 10ns period (100 MHz) ─────
    initial clk = 0;
    always #5 clk = ~clk;

    // ── VCD dump ─────────────────────────────────────────────
    initial begin
        $dumpfile("sim/rf_dump.vcd");
        $dumpvars(0, tb_register_file);
    end

    // ── Helper task ───────────────────────────────────────────
    integer pass_count, fail_count;

    task check_read;
        input [31:0] actual;
        input [31:0] expected;
        input [80*8:1] test_name;
        begin
            if (actual === expected) begin
                $display("  PASS  %-35s | got=%0d", test_name, actual);
                pass_count = pass_count + 1;
            end else begin
                $display("  FAIL  %-35s | got=%0d, expected=%0d",
                         test_name, actual, expected);
                fail_count = fail_count + 1;
            end
        end
    endtask

    // ── Main test sequence ────────────────────────────────────
    initial begin
        pass_count = 0; fail_count = 0;
        reg_write = 0;
        rd_addr = 0; rd_data = 0;
        rs1_addr = 0; rs2_addr = 0;

        $display("\n========================================");
        $display("  Register File Testbench Starting...");
        $display("========================================\n");

        // ── TEST 1: x0 is always 0 ───────────────────────────
        $display("--- x0 hardwired to zero ---");
        rs1_addr = 5'd0;
        #1;
        check_read(rs1_data, 32'd0, "read x0 = 0 (no write)");

        // Try writing to x0 — should have no effect
        @(negedge clk);
        rd_addr = 5'd0; rd_data = 32'hDEADBEEF; reg_write = 1;
        @(posedge clk); #1;
        reg_write = 0;
        rs1_addr = 5'd0;
        #1;
        check_read(rs1_data, 32'd0, "write to x0 ignored, still 0");

        // ── TEST 2: Write then read back ──────────────────────
        $display("\n--- Write and Read Back ---");

        @(negedge clk);
        rd_addr = 5'd1; rd_data = 32'd42; reg_write = 1;
        @(posedge clk); #1;
        reg_write = 0;
        rs1_addr = 5'd1;
        #1;
        check_read(rs1_data, 32'd42, "write 42 to x1, read x1");

        @(negedge clk);
        rd_addr = 5'd5; rd_data = 32'd100; reg_write = 1;
        @(posedge clk); #1;
        reg_write = 0;
        rs1_addr = 5'd5;
        #1;
        check_read(rs1_data, 32'd100, "write 100 to x5, read x5");

        @(negedge clk);
        rd_addr = 5'd31; rd_data = 32'hCAFEBABE; reg_write = 1;
        @(posedge clk); #1;
        reg_write = 0;
        rs1_addr = 5'd31;
        #1;
        check_read(rs1_data, 32'hCAFEBABE, "write to x31, read x31");

        // ── TEST 3: Dual read ports same cycle ────────────────
        $display("\n--- Dual Read Ports ---");

        // Write x2 = 200, x3 = 300
        @(negedge clk);
        rd_addr = 5'd2; rd_data = 32'd200; reg_write = 1;
        @(posedge clk); #1;
        @(negedge clk);
        rd_addr = 5'd3; rd_data = 32'd300; reg_write = 1;
        @(posedge clk); #1;
        reg_write = 0;

        // Read both in same cycle
        rs1_addr = 5'd2; rs2_addr = 5'd3;
        #1;
        check_read(rs1_data, 32'd200, "dual read: rs1=x2 → 200");
        check_read(rs2_data, 32'd300, "dual read: rs2=x3 → 300");

        // ── TEST 4: reg_write = 0, value should NOT change ────
        $display("\n--- Write Disabled ---");
        rs1_addr = 5'd1;
        @(negedge clk);
        rd_addr = 5'd1; rd_data = 32'd999; reg_write = 0; // write disabled
        @(posedge clk); #1;
        rs1_addr = 5'd1;
        #1;
        check_read(rs1_data, 32'd42, "reg_write=0: x1 stays 42");

        // ── TEST 5: Overwrite a register ─────────────────────
        $display("\n--- Overwrite Register ---");
        @(negedge clk);
        rd_addr = 5'd1; rd_data = 32'd999; reg_write = 1;
        @(posedge clk); #1;
        reg_write = 0;
        rs1_addr = 5'd1;
        #1;
        check_read(rs1_data, 32'd999, "overwrite x1: now 999");

        // ── Summary ───────────────────────────────────────────
        $display("\n========================================");
        $display("  Results: %0d passed, %0d failed", pass_count, fail_count);
        $display("========================================\n");

        $finish;
    end

endmodule

sim/rf_dump.vcd
$date
	Fri May 29 01:29:26 2026
$end
$version
	Icarus Verilog
$end
$timescale
	1ps
$end
$scope module tb_register_file $end
$var wire 32 ! rs2_data [31:0] $end
$var wire 32 " rs1_data [31:0] $end
$var reg 1 # clk $end
$var reg 5 $ rd_addr [4:0] $end
$var reg 32 % rd_data [31:0] $end
$var reg 1 & reg_write $end
$var reg 5 ' rs1_addr [4:0] $end
$var reg 5 ( rs2_addr [4:0] $end
$var integer 32 ) fail_count [31:0] $end
$var integer 32 * pass_count [31:0] $end
$scope module uut $end
$var wire 1 # clk $end
$var wire 5 + rd_addr [4:0] $end
$var wire 32 , rd_data [31:0] $end
$var wire 1 & reg_write $end
$var wire 5 - rs1_addr [4:0] $end
$var wire 5 . rs2_addr [4:0] $end
$var wire 32 / rs2_data [31:0] $end
$var wire 32 0 rs1_data [31:0] $end
$var integer 32 1 i [31:0] $end
$upscope $end
$scope task check_read $end
$var reg 32 2 actual [31:0] $end
$var reg 32 3 expected [31:0] $end
$var reg 640 4 test_name [640:1] $end
$upscope $end
$upscope $end
$enddefinitions $end
$comment Show the parameter values. $end
$dumpall
$end
#0
$dumpvars
bx 4
bx 3
bx 2
b100000 1
b0 0
b0 /
b0 .
b0 -
b0 ,
b0 +
b0 *
b0 )
b0 (
b0 '
0&
b0 %
b0 $
0#
b0 "
b0 !
$end
#1000
b1 *
b1110010011001010110000101100100001000000111100000110000001000000011110100100000001100000010000000101000011011100110111100100000011101110111001001101001011101000110010100101001 4
b0 3
b0 2
#5000
1#
#10000
1&
b11011110101011011011111011101111 %
b11011110101011011011111011101111 ,
0#
#15000
1#
#16000
0&
#17000
b10 *
b1110111011100100110100101110100011001010010000001110100011011110010000001111000001100000010000001101001011001110110111001101111011100100110010101100100001011000010000001110011011101000110100101101100011011000010000000110000 4
#20000
1&
b101010 %
b101010 ,
b1 $
b1 +
0#
#25000
1#
#26000
b101010 "
b101010 0
b1 '
b1 -
0&
#27000
b11 *
b111011101110010011010010111010001100101001000000011010000110010001000000111010001101111001000000111100000110001001011000010000001110010011001010110000101100100001000000111100000110001 4
b101010 3
b101010 2
#30000
1&
b1100100 %
b1100100 ,
b101 $
b101 +
0#
#35000
1#
#36000
b1100100 "
b1100100 0
b101 '
b101 -
0&
#37000
b100 *
b11101110111001001101001011101000110010100100000001100010011000000110000001000000111010001101111001000000111100000110101001011000010000001110010011001010110000101100100001000000111100000110101 4
b1100100 3
b1100100 2
#40000
1&
b11001010111111101011101010111110 %
b11001010111111101011101010111110 ,
b11111 $
b11111 +
0#
#45000
1#
#46000
b11001010111111101011101010111110 "
b11001010111111101011101010111110 0
b11111 '
b11111 -
0&
#47000
b101 *
b1110111011100100110100101110100011001010010000001110100011011110010000001111000001100110011000100101100001000000111001001100101011000010110010000100000011110000011001100110001 4
b11001010111111101011101010111110 3
b11001010111111101011101010111110 2
#50000
1&
b11001000 %
b11001000 ,
b10 $
b10 +
0#
#55000
1#
#60000
b100101100 %
b100101100 ,
b11 $
b11 +
0#
#65000
1#
#66000
b100101100 !
b100101100 /
b11001000 "
b11001000 0
b11 (
b11 .
b10 '
b10 -
0&
#67000
b101010 "
b101010 0
b1 '
b1 -
b111 *
b1100100011101010110000101101100001000000111001001100101011000010110010000111010001000000111001001110011001100100011110101111000001100111111111111111111111111111001001000100000001100110011000000110000 4
b100101100 3
b100101100 2
#70000
b1111100111 %
b1111100111 ,
b1 $
b1 +
0#
#75000
1#
#77000
b1000 *
b11100100110010101100111010111110111011101110010011010010111010001100101001111010011000000111010001000000111100000110001001000000111001101110100011000010111100101110011001000000011010000110010 4
b101010 3
b101010 2
#80000
1&
0#
#85000
b1111100111 "
b1111100111 0
1#
#86000
0&
#87000
b1001 *
b11011110111011001100101011100100111011101110010011010010111010001100101001000000111100000110001001110100010000001101110011011110111011100100000001110010011100100111001 4
b1111100111 3
b1111100111 2
